{
  "hash": "82392edd",
  "configHash": "f42f905b",
  "lockfileHash": "98c59ce4",
  "browserHash": "223913c8",
  "optimized": {
    "@alpinejs/focus": {
      "src": "../../../node_modules/@alpinejs/focus/dist/module.esm.js",
      "file": "@alpinejs_focus.js",
      "fileHash": "5d53212c",
      "needsInterop": false
    },
    "alpinejs": {
      "src": "../../../node_modules/alpinejs/dist/module.esm.js",
      "file": "alpinejs.js",
      "fileHash": "611c7bb4",
      "needsInterop": false
    },
    "axios": {
      "src": "../../../node_modules/axios/index.js",
      "file": "axios.js",
      "fileHash": "92192d55",
      "needsInterop": false
    }
  },
  "chunks": {
    "chunk-PZ5AY32C": {
      "file": "chunk-PZ5AY32C.js"
    }
  }
}